easyselenium/Example.py
easyselenium/__init__.py
easyselenium/easyselenium.py
easyselenium/webdriver_manager/__init__.py
easyselenium/webdriver_manager/archive.py
easyselenium/webdriver_manager/chrome.py
easyselenium/webdriver_manager/driver.py
easyselenium/webdriver_manager/driver_cache.py
easyselenium/webdriver_manager/firefox.py
easyselenium/webdriver_manager/manager.py
easyselenium/webdriver_manager/microsoft.py
easyselenium/webdriver_manager/opera.py
easyselenium/webdriver_manager/utils.py
easyselenium-1.4.dist-info/METADATA
easyselenium-1.4.dist-info/WHEEL
easyselenium-1.4.dist-info/licence.txt
easyselenium-1.4.dist-info/top_level.txt
easyselenium-1.4.dist-info/RECORD
