Metadata-Version: 2.1
Name: easyselenium
Version: 1.4
Summary: This is a selenium easy library which has easy syntax build on selenium.all the things are running in background we are calling only functions..This is too easy for begineers
Home-page: https://github.com/ankitk29kothari/Step2success/tree/master/Selenium-Web%20Automation/easy_selenium
Author: Ankit Kothari
Author-email: ankit.kothari@hotmail.com
License: GPLv2
Download-URL: https://github.com/ankitk29kothari/Step2success/tree/master/Selenium-Web%20Automation/easy_selenium
Keywords: selenium,ankit kothari,step2success,easyselenium,easy-selenium,python selenium,selenium webdriver
Platform: UNKNOWN
Classifier: Programming Language :: Python
Requires-Python: >=3.6
Requires-Dist: setuptools
Requires-Dist: selenium
Requires-Dist: webdriver-manager
